easy_dp/PrivacyEngine.py
easy_dp/Sampler.py
easy_dp/__init__.py
easy_dp/accounting_manager.py
easy_dp/rdp_accounting.py
easy_dp-0.1.0.dist-info/METADATA
easy_dp-0.1.0.dist-info/WHEEL
easy_dp-0.1.0.dist-info/top_level.txt
easy_dp-0.1.0.dist-info/RECORD
