Metadata-Version: 2.1
Name: easy_dp
Version: 0.1.0
Summary: A not-so-efficient library for easy implementation of multi-gpu differential privacy
Author-email: Tarasco Pier Paolo <pier.tarasco@gmail.com>
Project-URL: Homepage, https://github.com/Pier297/easy_dp
Project-URL: Bug Tracker, https://github.com/Pier297/easy_dp/issues
Classifier: Programming Language :: Python :: 3
Classifier: License :: OSI Approved :: MIT License
Classifier: Operating System :: OS Independent
Requires-Python: >=3.7
